Workbook

Sheet Resumen
A1: Reactafy — progreso del backlog
A2: Se calcula solo a partir de la columna Estado de la hoja Backlog.
A4: Épica | B4: Total | C4: ✅ Terminado | D4: 🔄 En curso | E4: % terminado
A5: 1. Arquitectura e infraestructura técnica | B5: =COUNTIF(Backlog!$C$2:$C$145,A5) -> 20 | C5: =COUNTIFS(Backlog!$C$2:$C$145,A5,Backlog!$A$2:$A$145,"✅ Terminado") -> 0 | D5: =COUNTIFS(Backlog!$C$2:$C$145,A5,Backlog!$A$2:$A$145,"🔄 En curso") -> 0 | E5: =IF(B5=0,0,C5/B5) -> 0
A6: 2. Listado de productos (PLP) | B6: =COUNTIF(Backlog!$C$2:$C$145,A6) -> 22 | C6: =COUNTIFS(Backlog!$C$2:$C$145,A6,Backlog!$A$2:$A$145,"✅ Terminado") -> 0 | D6: =COUNTIFS(Backlog!$C$2:$C$145,A6,Backlog!$A$2:$A$145,"🔄 En curso") -> 0 | E6: =IF(B6=0,0,C6/B6) -> 0
A7: 3. Página de producto (PDP) | B7: =COUNTIF(Backlog!$C$2:$C$145,A7) -> 18 | C7: =COUNTIFS(Backlog!$C$2:$C$145,A7,Backlog!$A$2:$A$145,"✅ Terminado") -> 0 | D7: =COUNTIFS(Backlog!$C$2:$C$145,A7,Backlog!$A$2:$A$145,"🔄 En curso") -> 0 | E7: =IF(B7=0,0,C7/B7) -> 0
A8: 4. Carrito y checkout | B8: =COUNTIF(Backlog!$C$2:$C$145,A8) -> 17 | C8: =COUNTIFS(Backlog!$C$2:$C$145,A8,Backlog!$A$2:$A$145,"✅ Terminado") -> 0 | D8: =COUNTIFS(Backlog!$C$2:$C$145,A8,Backlog!$A$2:$A$145,"🔄 En curso") -> 0 | E8: =IF(B8=0,0,C8/B8) -> 0
A9: 5. Autenticación y cuenta de cliente | B9: =COUNTIF(Backlog!$C$2:$C$145,A9) -> 19 | C9: =COUNTIFS(Backlog!$C$2:$C$145,A9,Backlog!$A$2:$A$145,"✅ Terminado") -> 1 | D9: =COUNTIFS(Backlog!$C$2:$C$145,A9,Backlog!$A$2:$A$145,"🔄 En curso") -> 2 | E9: =IF(B9=0,0,C9/B9) -> 0.052631579
A10: 6. Layout y contenido | B10: =COUNTIF(Backlog!$C$2:$C$145,A10) -> 18 | C10: =COUNTIFS(Backlog!$C$2:$C$145,A10,Backlog!$A$2:$A$145,"✅ Terminado") -> 0 | D10: =COUNTIFS(Backlog!$C$2:$C$145,A10,Backlog!$A$2:$A$145,"🔄 En curso") -> 0 | E10: =IF(B10=0,0,C10/B10) -> 0
A11: 7. Puesta en producción (go-live) | B11: =COUNTIF(Backlog!$C$2:$C$145,A11) -> 30 | C11: =COUNTIFS(Backlog!$C$2:$C$145,A11,Backlog!$A$2:$A$145,"✅ Terminado") -> 0 | D11: =COUNTIFS(Backlog!$C$2:$C$145,A11,Backlog!$A$2:$A$145,"🔄 En curso") -> 0 | E11: =IF(B11=0,0,C11/B11) -> 0
A12: Total | B12: =SUM(B5:B11) -> 144 | C12: =SUM(C5:C11) -> 1 | D12: =SUM(D5:D11) -> 2 | E12: =IF(B12=0,0,C12/B12) -> 0.0069444444
A14: Glosario
A15: Backlog | B15: Lista ordenada de todo el trabajo pendiente del producto.
A16: Épica | B16: Bloque grande de trabajo con un objetivo común; dura varias semanas.
A17: Historia de usuario | B17: Algo que el cliente nota: «como cliente, quiero filtrar por marca».
A18: Tarea técnica | B18: Trabajo necesario que el usuario no ve (caché, SEO, despliegue).
A19: Spike | B19: Investigación o decisión acotada en el tiempo, antes de construir.
A20: QA | B20: Quality Assurance: pruebas.
A21: Bloqueada por | B21: Tarea que tiene que estar hecha antes (en Jira, «blocked by»).
A22: PLP / PDP | B22: Product Listing Page (listado) / Product Detail Page (ficha).
A23: Go-live | B23: Puesta en producción: el día que el sistema nuevo sustituye al antiguo.
A24: Estado | B24: Cámbialo en la hoja Backlog con el desplegable: ⬜ Pendiente, 🔄 En curso, ✅ Terminado.

Sheet Backlog
A1: Estado | B1: ID | C1: Épica | D1: Tipo | E1: Historia / tarea | F1: Subtarea | G1: Descripción | H1: Área | I1: Bloqueada por
A2: ⬜ Pendiente | B2: 1 | C2: 1. Arquitectura e infraestructura técnica | D2: Tarea técnica | E2: Enrutado Next / WordPress | F2: Definir hostname de origen de WordPress | G2: aguafy.com apuntará a Next; WordPress necesita otro nombre (p. ej. wp.aguafy.com o el origen de Hostinger) para que Next le reenvíe lo que no sirva él. | H2: Spike / decisión
A3: ⬜ Pendiente | B3: 2 | C3: 1. Arquitectura e infraestructura técnica | D3: Tarea técnica | E3: Enrutado Next / WordPress | F3: Listar lo que sigue sirviendo WordPress | G3: Blog (artículos en la raíz /{slug}/ y /category/), checkout (/finalizar-compra/), wp-admin, wp-login, wp-json, wp-content (imágenes), feeds. | H3: Spike / decisión
A4: ⬜ Pendiente | B4: 3 | C4: 1. Arquitectura e infraestructura técnica | D4: Tarea técnica | E4: Enrutado Next / WordPress | F4: Reenvío automático a WordPress (fallback) | G4: En next.config usar rewrites.fallback: toda URL que Next no tenga se sirve desde WordPress. Así el blog y cualquier página nueva de WP funcionan sin mantener una lista a mano. | H4: Frontend (Next) | I4: Definir hostname de origen de WordPress
A5: ⬜ Pendiente | B5: 4 | C5: 1. Arquitectura e infraestructura técnica | D5: Tarea técnica | E5: Enrutado Next / WordPress | F5: Comprobar cookies entre Next y WordPress | G5: Que la sesión y el carrito sobrevivan al ir al checkout de WP y volver (dominio de las cookies, SameSite). | H5: Frontend + Backend | I5: Reenvío automático a WordPress (fallback)
A6: ⬜ Pendiente | B6: 5 | C6: 1. Arquitectura e infraestructura técnica | D6: Tarea técnica | E6: Enrutado Next / WordPress | F6: Probar el blog servido a través de Next | G6: Abrir 3 artículos, una categoría de blog y el feed; deben verse igual que hoy, con sus canonical apuntando a aguafy.com. | H6: QA | I6: Reenvío automático a WordPress (fallback)
A7: ⬜ Pendiente | B7: 6 | C7: 1. Arquitectura e infraestructura técnica | D7: Tarea técnica | E7: Enrutado Next / WordPress | F7: Enlaces del menú y pie al blog | G7: El enlace 'Blog' del menú apunta a /blog (que hoy no existe en el sitemap): confirmar la URL real del listado. | H7: Spike / decisión
A8: ⬜ Pendiente | B8: 7 | C8: 1. Arquitectura e infraestructura técnica | D8: Tarea técnica | E8: URLs de producto con slug | F8: Decidir slug de padre o de variación | G8: aguafy.com usa el slug del producto padre (/producto/acqua-panna/). Decidir cómo se selecciona la variación dentro (parámetro, selector) sin crear URLs duplicadas. | H8: Spike / decisión
A9: ⬜ Pendiente | B9: 8 | C9: 1. Arquitectura e infraestructura técnica | D9: Tarea técnica | E9: URLs de producto con slug | F9: API: devolver slug en cada producto | G9: Añadir 'slug' (y el del padre) en reactafy_get_product_summary. | H9: Backend (WordPress)
A10: ⬜ Pendiente | B10: 9 | C10: 1. Arquitectura e infraestructura técnica | D10: Tarea técnica | E10: URLs de producto con slug | F10: API: buscar producto por slug | G10: Nuevo endpoint o parámetro: /products/by-slug/{slug} que devuelva el grupo y sus variaciones. | H10: Backend (WordPress) | I10: API: devolver slug en cada producto
A11: ⬜ Pendiente | B11: 10 | C11: 1. Arquitectura e infraestructura técnica | D11: Tarea técnica | E11: URLs de producto con slug | F11: Mover la ruta a app/producto/[slug] | G11: Sustituir app/producto/[id]; 404 si el slug no existe. | H11: Frontend (Next) | I11: API: buscar producto por slug
A12: ⬜ Pendiente | B12: 11 | C12: 1. Arquitectura e infraestructura técnica | D12: Tarea técnica | E12: URLs de producto con slug | F12: Actualizar enlaces | G12: Tarjetas, carrito, página de pedido y cualquier Link a /producto/{id}. | H12: Frontend (Next) | I12: Mover la ruta a app/producto/[slug]
A13: ⬜ Pendiente | B13: 12 | C13: 1. Arquitectura e infraestructura técnica | D13: Tarea técnica | E13: URLs de producto con slug | F13: Probar las 50 URLs del sitemap | G13: Recorrer las URLs de producto del sitemap actual y comprobar que todas abren en Reactafy. | H13: QA | I13: Actualizar enlaces
A14: ⬜ Pendiente | B14: 13 | C14: 1. Arquitectura e infraestructura técnica | D14: Tarea técnica | E14: Caché del catálogo en Next | F14: Leer la documentación de caché de Next 16 | G14: AGENTS.md avisa de cambios: revisar node_modules/next/dist/docs (use cache / revalidate) antes de elegir. | H14: Frontend (Next)
A15: ⬜ Pendiente | B15: 14 | C15: 1. Arquitectura e infraestructura técnica | D15: Tarea técnica | E15: Caché del catálogo en Next | F15: Cachear la lista de productos | G15: getProducts cacheado por página y filtros, con un tiempo de revalidación. | H15: Frontend (Next) | I15: Leer la documentación de caché de Next 16
A16: ⬜ Pendiente | B16: 15 | C16: 1. Arquitectura e infraestructura técnica | D16: Tarea técnica | E16: Caché del catálogo en Next | F16: Cachear la ficha de producto | G16: getProduct por slug cacheado. | H16: Frontend (Next) | I16: URLs de producto con slug
A17: ⬜ Pendiente | B17: 16 | C17: 1. Arquitectura e infraestructura técnica | D17: Tarea técnica | E17: Caché del catálogo en Next | F17: Etiquetas de caché por producto | G17: Etiquetar cada respuesta (producto, marca, categoría) para poder invalidar solo lo que cambia. | H17: Frontend (Next) | I17: Cachear la lista de productos
A18: ⬜ Pendiente | B18: 17 | C18: 1. Arquitectura e infraestructura técnica | D18: Tarea técnica | E18: Caché del catálogo en Next | F18: Ruta de revalidación en Next | G18: Endpoint protegido con el secreto compartido que invalida etiquetas. | H18: Frontend (Next) | I18: Etiquetas de caché por producto
A19: ⬜ Pendiente | B19: 18 | C19: 1. Arquitectura e infraestructura técnica | D19: Tarea técnica | E19: Caché del catálogo en Next | F19: Aviso desde WordPress al guardar | G19: Hook al guardar producto, variación o regla de ADP que llama a la ruta de revalidación de Next y purga LiteSpeed. | H19: Backend (WordPress) | I19: Ruta de revalidación en Next
A20: ⬜ Pendiente | B20: 19 | C20: 1. Arquitectura e infraestructura técnica | D20: Tarea técnica | E20: Caché del catálogo en Next | F20: TTL de respaldo | G20: Tiempo máximo de caché aunque falle el aviso (reglas de ADP con fechas no disparan ningún guardado). | H20: Frontend (Next)
A21: ⬜ Pendiente | B21: 20 | C21: 1. Arquitectura e infraestructura técnica | D21: Tarea técnica | E21: Caché del catálogo en Next | F21: Medir en modo producción | G21: next build && next start; comparar /tienda y una ficha con los ~157 ms de aguafy.com. | H21: QA | I21: Cachear la ficha de producto
A22: ⬜ Pendiente | B22: 21 | C22: 2. Listado de productos (PLP) | D22: Historia de usuario | E22: Filtros y orden de la tienda | F22: API: opciones de filtro | G22: Endpoint que devuelva marcas, tipos de envase y características con sus slugs, leídos de las taxonomías/atributos de Woo. | H22: Backend (WordPress)
A23: ⬜ Pendiente | B23: 22 | C23: 2. Listado de productos (PLP) | D23: Historia de usuario | E23: Filtros y orden de la tienda | F23: API: filtrar productos | G23: Parámetros brand, envase, caracteristica en /products (combinables). | H23: Backend (WordPress)
A24: ⬜ Pendiente | B24: 23 | C24: 2. Listado de productos (PLP) | D24: Historia de usuario | E24: Filtros y orden de la tienda | F24: API: ordenar productos | G24: Parámetro orderby: menu_order, price, price-desc (el orden por precio debe usar el precio de invitado). | H24: Backend (WordPress)
A25: ⬜ Pendiente | B25: 24 | C25: 2. Listado de productos (PLP) | D25: Historia de usuario | E25: Filtros y orden de la tienda | F25: Estado en la URL | G25: Leer y escribir filtros y orden en searchParams; al cambiar filtro vuelve a la primera página. | H25: Frontend (Next) | I25: API: filtrar productos
A26: ⬜ Pendiente | B26: 25 | C26: 2. Listado de productos (PLP) | D26: Historia de usuario | E26: Filtros y orden de la tienda | F26: Componente de filtros | G26: Casillas de marca, envase y características; botón 'Limpiar filtros'. | H26: Frontend (Next) | I26: API: opciones de filtro
A27: ⬜ Pendiente | B27: 26 | C27: 2. Listado de productos (PLP) | D27: Historia de usuario | E27: Filtros y orden de la tienda | F27: Selector de orden | G27: Por defecto / precio menor a mayor / precio mayor a menor. | H27: Frontend (Next) | I27: API: ordenar productos
A28: ⬜ Pendiente | B28: 27 | C28: 2. Listado de productos (PLP) | D28: Historia de usuario | E28: Filtros y orden de la tienda | F28: Filtros en móvil | G28: Panel desplegable para pantallas pequeñas. | H28: Frontend (Next) | I28: Componente de filtros
A29: ⬜ Pendiente | B29: 28 | C29: 2. Listado de productos (PLP) | D29: Historia de usuario | E29: Filtros y orden de la tienda | F29: Sin resultados | G29: Mensaje y acceso a limpiar filtros cuando la combinación no devuelve nada. | H29: Frontend (Next) | I29: Estado en la URL
A30: ⬜ Pendiente | B30: 29 | C30: 2. Listado de productos (PLP) | D30: Historia de usuario | E30: Filtros y orden de la tienda | F30: Cargar más con filtros | G30: 'Cargar más' / scroll infinito respeta los filtros activos. | H30: Frontend (Next) | I30: Estado en la URL
A31: ⬜ Pendiente | B31: 30 | C31: 2. Listado de productos (PLP) | D31: Historia de usuario | E31: Páginas de marca y categoría | F31: Ruta /brand/[slug] | G31: Tienda con filtro de marca fijo; 404 si la marca no existe. | H31: Frontend (Next) | I31: Filtros y orden de la tienda
A32: ⬜ Pendiente | B32: 31 | C32: 2. Listado de productos (PLP) | D32: Historia de usuario | E32: Páginas de marca y categoría | F32: Banner de marca | G32: Mostrar el banner de la marca (datos desde WP). | H32: Frontend + Backend | I32: Ruta /brand/[slug]
A33: ⬜ Pendiente | B33: 32 | C33: 2. Listado de productos (PLP) | D33: Historia de usuario | E33: Páginas de marca y categoría | F33: Ruta /categoria-producto/[...slug] | G33: Incluye subcategorías (agua/agua-gasificada). | H33: Frontend (Next) | I33: Filtros y orden de la tienda
A34: ⬜ Pendiente | B34: 33 | C34: 2. Listado de productos (PLP) | D34: Historia de usuario | E34: Páginas de marca y categoría | F34: Título y descripción de marca/categoría | G34: Nombre y texto de la taxonomía como h1 y metadatos. | H34: Frontend (Next)
A35: ⬜ Pendiente | B35: 34 | C35: 2. Listado de productos (PLP) | D35: Historia de usuario | E35: Páginas de marca y categoría | F35: Probar las 22 marcas y 6 categorías | G35: Recorrer las URLs del sitemap. | H35: QA | I35: Ruta /categoria-producto/[...slug]
A36: ⬜ Pendiente | B36: 35 | C36: 2. Listado de productos (PLP) | D36: Historia de usuario | E36: Insignias y agotados | F36: Insignia 'Nuevo' | G36: Desde editorial.isNew. | H36: Frontend (Next)
A37: ⬜ Pendiente | B37: 36 | C37: 2. Listado de productos (PLP) | D37: Historia de usuario | E37: Insignias y agotados | F37: Insignia 'Últimas unidades' | G37: Desde editorial.isLowStock. | H37: Frontend (Next)
A38: ⬜ Pendiente | B38: 37 | C38: 2. Listado de productos (PLP) | D38: Historia de usuario | E38: Insignias y agotados | F38: Insignia de descuento | G38: Cuando el precio tiene 'Desde' o hay regla de ADP activa (dato desde WP). | H38: Frontend + Backend
A39: ⬜ Pendiente | B39: 38 | C39: 2. Listado de productos (PLP) | D39: Historia de usuario | E39: Insignias y agotados | F39: Producto agotado | G39: Se muestra con aviso y sin botón de añadir (stock.status = out_of_stock). | H39: Frontend (Next)
A40: ⬜ Pendiente | B40: 39 | C40: 2. Listado de productos (PLP) | D40: Historia de usuario | E40: Búsqueda | F40: API: parámetro search | G40: Búsqueda en Woo por nombre, marca y SKU. | H40: Backend (WordPress)
A41: ⬜ Pendiente | B41: 40 | C41: 2. Listado de productos (PLP) | D41: Historia de usuario | E41: Búsqueda | F41: Búsqueda en /tienda?search= | G41: Combinable con filtros y orden. | H41: Frontend (Next) | I41: API: parámetro search
A42: ⬜ Pendiente | B42: 41 | C42: 2. Listado de productos (PLP) | D42: Historia de usuario | E42: Búsqueda | F42: Panel de búsqueda en la cabecera | G42: Resultados mientras escribes, con retardo y cancelación de peticiones anteriores. | H42: Frontend (Next) | I42: API: parámetro search
A43: ⬜ Pendiente | B43: 42 | C43: 2. Listado de productos (PLP) | D43: Historia de usuario | E43: Búsqueda | F43: Sin resultados de búsqueda | G43: Mensaje y sugerencia de ver toda la tienda. | H43: Frontend (Next)
A44: ⬜ Pendiente | B44: 43 | C44: 3. Página de producto (PDP) | D44: Historia de usuario | E44: Selector de variación | F44: Datos de las variaciones del grupo | G44: La ficha recibe todas las variaciones con sus atributos (sabor, tamaño). | H44: Backend (WordPress) | I44: URLs de producto con slug
A45: ⬜ Pendiente | B45: 44 | C45: 3. Página de producto (PDP) | D45: Historia de usuario | E45: Selector de variación | F45: Selector de sabor | G45: Botones/lista con los sabores disponibles. | H45: Frontend (Next) | I45: Datos de las variaciones del grupo
A46: ⬜ Pendiente | B46: 45 | C46: 3. Página de producto (PDP) | D46: Historia de usuario | E46: Selector de variación | F46: Selector de tamaño | G46: Solo tamaños disponibles para el sabor elegido. | H46: Frontend (Next) | I46: Selector de sabor
A47: ⬜ Pendiente | B47: 46 | C47: 3. Página de producto (PDP) | D47: Historia de usuario | E47: Selector de variación | F47: Cambiar imagen, precio y stock al elegir | G47: Sin recargar la página. | H47: Frontend (Next) | I47: Selector de tamaño
A48: ⬜ Pendiente | B48: 47 | C48: 3. Página de producto (PDP) | D48: Historia de usuario | E48: Selector de variación | F48: Variación en la URL | G48: Parámetro para compartir una variación concreta sin crear URL indexable nueva (canonical al padre). | H48: Frontend (Next) | I48: Selector de tamaño
A49: ⬜ Pendiente | B49: 48 | C49: 3. Página de producto (PDP) | D49: Historia de usuario | E49: Precio por cantidad y pedido mínimo | F49: API: tabla de descuentos de ADP | G49: Devolver los tramos (desde X unidades → precio) calculados por ADP. | H49: Backend (WordPress)
A50: ⬜ Pendiente | B50: 49 | C50: 3. Página de producto (PDP) | D50: Historia de usuario | E50: Precio por cantidad y pedido mínimo | F50: Tabla de descuentos en la ficha | G50: Mostrar los tramos; se oculta si no hay. | H50: Frontend (Next) | I50: API: tabla de descuentos de ADP
A51: ⬜ Pendiente | B51: 50 | C51: 3. Página de producto (PDP) | D51: Historia de usuario | E51: Precio por cantidad y pedido mínimo | F51: API: pedido mínimo | G51: Exponer el importe mínimo desde la configuración real de WooCommerce. | H51: Backend (WordPress)
A52: ⬜ Pendiente | B52: 51 | C52: 3. Página de producto (PDP) | D52: Historia de usuario | E52: Precio por cantidad y pedido mínimo | F52: Aviso de pedido mínimo y envío gratis | G52: Texto con el importe que devuelve la API. | H52: Frontend (Next) | I52: API: pedido mínimo
A53: ⬜ Pendiente | B53: 52 | C53: 3. Página de producto (PDP) | D53: Historia de usuario | E53: Resto de la ficha | F53: Contenido: SKU y '15 botellas de 750 ml' | G53: Desde atributos cantidad y volumen. | H53: Frontend (Next)
A54: ⬜ Pendiente | B54: 53 | C54: 3. Página de producto (PDP) | D54: Historia de usuario | E54: Resto de la ficha | F54: Cantidad − / + y añadir al carrito | G54: Con estado de carga y error. | H54: Frontend (Next)
A55: ⬜ Pendiente | B55: 54 | C55: 3. Página de producto (PDP) | D55: Historia de usuario | E55: Resto de la ficha | F55: '(N cajas en tu cesta)' | G55: Unidades de esa variación ya en el carrito, desde CartContext. | H55: Frontend (Next)
A56: ⬜ Pendiente | B56: 55 | C56: 3. Página de producto (PDP) | D56: Historia de usuario | E56: Resto de la ficha | F56: Pestaña 'Características' | G56: Atributos del producto. | H56: Frontend (Next)
A57: ⬜ Pendiente | B57: 56 | C57: 3. Página de producto (PDP) | D57: Historia de usuario | E57: Resto de la ficha | F57: Pestaña 'Sobre la marca' | G57: Descripción de la marca (dato desde WP). | H57: Frontend + Backend
A58: ⬜ Pendiente | B58: 57 | C58: 3. Página de producto (PDP) | D58: Historia de usuario | E58: Resto de la ficha | F58: Migas de pan | G58: Tienda › Marca › Producto, con datos estructurados. | H58: Frontend (Next)
A59: ⬜ Pendiente | B59: 58 | C59: 3. Página de producto (PDP) | D59: Historia de usuario | E59: Resto de la ficha | F59: Relacionados 'Te puede interesar' | G59: Slider con productos relacionados (fuente: WP). | H59: Frontend + Backend
A60: ⬜ Pendiente | B60: 59 | C60: 3. Página de producto (PDP) | D60: Historia de usuario | E60: Resto de la ficha | F60: Banners de ficha | G60: CPT banner-single-prod asociado al producto. | H60: Frontend + Backend
A61: ⬜ Pendiente | B61: 60 | C61: 3. Página de producto (PDP) | D61: Historia de usuario | E61: Resto de la ficha | F61: Galería/imagen optimizada | G61: Imagen principal con prioridad alta y tamaños correctos. | H61: Frontend (Next)
A62: ⬜ Pendiente | B62: 61 | C62: 4. Carrito y checkout | D62: Historia de usuario | E62: Carrito en panel lateral | F62: Componente de panel lateral | G62: Se abre al añadir y desde la cabecera; se cierra con Esc y fondo. | H62: Frontend (Next)
A63: ⬜ Pendiente | B63: 62 | C63: 4. Carrito y checkout | D63: Historia de usuario | E63: Carrito en panel lateral | F63: Líneas del carrito | G63: Imagen, nombre, contenido, precio, cantidad − / +, eliminar. | H63: Frontend (Next)
A64: ⬜ Pendiente | B64: 63 | C64: 4. Carrito y checkout | D64: Historia de usuario | E64: Carrito en panel lateral | F64: Resumen | G64: Subtotal, tasas y nota 'envío calculado en checkout'. | H64: Frontend (Next)
... A68: ⬜ Pendiente | B68: 67 | C68: 4. Carrito y checkout | D68: Historia de usuario | E68: Carrito en panel lateral | F68: Botón 'Finalizar compra' | G68: Lleva al checkout de WordPress con la sesión transferida. | H68: Frontend (Next)
A69: ⬜ Pendiente | B69: 68 | C69: 4. Carrito y checkout | D69: Historia de usuario | E69: Pedido mínimo en el carrito | F69: API: lo que falta para el mínimo | G69: Calculado por Woo con el carrito real. | H69: Backend (WordPress) | I69: API: pedido mínimo
A70: ⬜ Pendiente | B70: 69 | C70: 4. Carrito y checkout | D70: Historia de usuario | E70: Pedido mínimo en el carrito | F70: Barra 'Te faltan MXN X' | G70: Progreso hacia el mínimo. | H70: Frontend (Next) | I70: API: lo que falta para el mínimo
A71: ⬜ Pendiente | B71: 70 | C71: 4. Carrito y checkout | D71: Historia de usuario | E71: Pedido mínimo en el carrito | F71: Bloquear 'Finalizar compra' | G71: Deshabilitado hasta llegar al mínimo; WooCommerce también lo valida. | H71: Frontend + Backend | I71: Barra 'Te faltan MXN X'
A72: ⬜ Pendiente | B72: 71 | C72: 4. Carrito y checkout | D72: Spike | E72: Cupones | F72: Decidir dónde se aplican | G72: ¿Solo en el checkout de WP o también en el carrito de Next? | H72: Spike / decisión
A73: ⬜ Pendiente | B73: 72 | C73: 4. Carrito y checkout | D73: QA | E73: Probar el checkout | F73: Invitado: compra completada | G73: Datos de facturación y envío, pago correcto, página de pedido. | H73: QA
A74: ⬜ Pendiente | B74: 73 | C74: 4. Carrito y checkout | D74: QA | E74: Probar el checkout | F74: Usuario logueado: compra completada | G74: Precios de su rol aplicados en el pedido. | H74: QA
A75: ⬜ Pendiente | B75: 74 | C75: 4. Carrito y checkout | D75: QA | E75: Probar el checkout | F75: Pago fallido | G75: Mensaje y posibilidad de reintentar. | H75: QA
A76: ⬜ Pendiente | B76: 75 | C76: 4. Carrito y checkout | D76: QA | E76: Probar el checkout | F76: Pago cancelado | G76: Vuelta al carrito sin perderlo. | H76: QA
A77: ⬜ Pendiente | B77: 76 | C77: 4. Carrito y checkout | D77: QA | E77: Probar el checkout | F77: Pedido por debajo del mínimo | G77: WooCommerce lo rechaza aunque se salte Next. | H77: QA
A78: ⬜ Pendiente | B78: 77 | C78: 4. Carrito y checkout | D78: QA | E78: Probar el checkout | F78: Cotización: imprimir PDF | G78: Paridad con /cotizacion/: resumen del carrito imprimible. | H78: Frontend (Next)
A79: ✅ Terminado | B79: 78 | C79: 5. Autenticación y cuenta de cliente | D79: Historia de usuario | E79: Registro | F79: Registro con email y contraseña | G79: Endpoint protegido con secreto, wc_create_new_customer, validación de contraseña. | H79: Frontend + Backend
A80: ⬜ Pendiente | B80: 79 | C80: 5. Autenticación y cuenta de cliente | D80: Historia de usuario | E80: Registro | F80: Conservar carrito del invitado al registrarse | G80: Probar: añadir como invitado, registrarse, el carrito sigue. | H80: QA
A81: ⬜ Pendiente | B81: 80 | C81: 5. Autenticación y cuenta de cliente | D81: Historia de usuario | E81: Registro | F81: Freno antibots | G81: reCAPTCHA o límite de intentos por IP en la ruta de Next. | H81: Frontend (Next)
A82: ⬜ Pendiente | B82: 81 | C82: 5. Autenticación y cuenta de cliente | D82: Historia de usuario | E82: Registro | F82: Enlaces entre login y registro | G82: Desde /login a /registro y al revés. | H82: Frontend (Next)
A83: ⬜ Pendiente | B83: 82 | C83: 5. Autenticación y cuenta de cliente | D83: Historia de usuario | E83: Recuperar contraseña | F83: API: solicitar recuperación | G83: Envía el email de WooCommerce/WordPress con el enlace (sin revelar si el email existe). | H83: Backend (WordPress)
A84: ⬜ Pendiente | B84: 83 | C84: 5. Autenticación y cuenta de cliente | D84: Historia de usuario | E84: Recuperar contraseña | F84: API: fijar nueva contraseña | G84: Valida el token y usa reactafy_validate_password. | H84: Backend (WordPress)
A85: 🔄 En curso | B85: 84 | C85: 5. Autenticación y cuenta de cliente | D85: Historia de usuario | E85: Recuperar contraseña | F85: Página 'He olvidado mi contraseña' | G85: Formulario de email. | H85: Frontend (Next) | I85: API: solicitar recuperación
A86: 🔄 En curso | B86: 85 | C86: 5. Autenticación y cuenta de cliente | D86: Historia de usuario | E86: Recuperar contraseña | F86: Página de nueva contraseña | G86: Recibe el token del enlace del email. | H86: Frontend (Next) | I86: API: fijar nueva contraseña
A87: ⬜ Pendiente | B87: 86 | C87: 5. Autenticación y cuenta de cliente | D87: Historia de usuario | E87: Recuperar contraseña | F87: Enlace del email apunta a Next | G87: El email de recuperación lleva a la página de Next, no a wp-login. | H87: Backend (WordPress) | I87: Página de nueva contraseña
A88: ⬜ Pendiente | B88: 87 | C88: 5. Autenticación y cuenta de cliente | D88: Historia de usuario | E88: Zona de usuario | F88: API: datos de la cuenta | G88: Solo del usuario autenticado por JWT. | H88: Backend (WordPress)
A89: ⬜ Pendiente | B89: 88 | C89: 5. Autenticación y cuenta de cliente | D89: Historia de usuario | E89: Zona de usuario | F89: API: lista de pedidos | G89: Paginada, solo del usuario autenticado. | H89: Backend (WordPress)
A90: ⬜ Pendiente | B90: 89 | C90: 5. Autenticación y cuenta de cliente | D90: Historia de usuario | E90: Zona de usuario | F90: API: detalle de pedido | G90: Comprobando que el pedido es del usuario. | H90: Backend (WordPress)
A91: ⬜ Pendiente | B91: 90 | C91: 5. Autenticación y cuenta de cliente | D91: Historia de usuario | E91: Zona de usuario | F91: Página de cuenta | G91: Datos del usuario. | H91: Frontend (Next) | I91: API: datos de la cuenta
A92: ⬜ Pendiente | B92: 91 | C92: 5. Autenticación y cuenta de cliente | D92: Historia de usuario | E92: Zona de usuario | F92: Historial de pedidos | G92: Listado con estado y total. | H92: Frontend (Next) | I92: API: lista de pedidos
A93: ⬜ Pendiente | B93: 92 | C93: 5. Autenticación y cuenta de cliente | D93: Historia de usuario | E93: Zona de usuario | F93: Detalle de pedido | G93: Líneas, totales, dirección y estado. | H93: Frontend (Next) | I93: API: detalle de pedido
A94: ⬜ Pendiente | B94: 93 | C94: 5. Autenticación y cuenta de cliente | D94: Historia de usuario | E94: Zona de usuario | F94: Cambiar contraseña | G94: Con reactafy_validate_password. | H94: Frontend + Backend
A95: ⬜ Pendiente | B95: 94 | C95: 5. Autenticación y cuenta de cliente | D95: Historia de usuario | E95: Zona de usuario | F95: Proteger las rutas de cuenta | G95: Redirigir a /login si no hay sesión. | H95: Frontend (Next)
A96: ⬜ Pendiente | B96: 95 | C96: 5. Autenticación y cuenta de cliente | D96: Tarea técnica | E96: Sesión | F96: Caducidad del JWT | G96: Detectar token caducado (401) y cerrar sesión limpia o pedir login, sin romper la página. | H96: Frontend (Next)
A97: ⬜ Pendiente | B97: 96 | C97: 5. Autenticación y cuenta de cliente | D97: Tarea técnica | E97: Sesión | F97: Unificar login | G97: Decidir qué pasa con /aguafy-login/ y /mi-cuenta/ (redirigir a las páginas de Next). | H97: Spike / decisión
A98: ⬜ Pendiente | B98: 97 | C98: 6. Layout y contenido | D98: Historia de usuario | E98: Cabecera y pie | F98: Menú principal | G98: Tienda, Somos, Contacto, Blog. | H98: Frontend (Next)
A99: ⬜ Pendiente | B99: 98 | C99: 6. Layout y contenido | D99: Historia de usuario | E99: Cabecera y pie | F99: Teléfono y WhatsApp | G99: En cabecera y pie. | H99: Frontend (Next)
A100: ⬜ Pendiente | B100: 99 | C100: 6. Layout y contenido | D100: Historia de usuario | E100: Cabecera y pie | F100: Acceso a cuenta / cerrar sesión | G100: Icono con estado según sesión. | H100: Frontend (Next)
A101: ⬜ Pendiente | B101: 100 | C101: 6. Layout y contenido | D101: Historia de usuario | E101: Cabecera y pie | F101: Menú móvil | G101: Toggle y panel lateral. | H101: Frontend (Next)
A102: ⬜ Pendiente | B102: 101 | C102: 6. Layout y contenido | D102: Historia de usuario | E102: Cabecera y pie | F102: Carrusel de marcas | G102: Logos de marcas enlazando a /brand/ (lista desde WP). | H102: Frontend + Backend
A103: ⬜ Pendiente | B103: 102 | C103: 6. Layout y contenido | D103: Historia de usuario | E103: Cabecera y pie | F103: Pie completo | G103: Bloques de servicio, enlaces, políticas, redes sociales. | H103: Frontend (Next)
...
